mtxcli/__init__.py
mtxcli/dc.py
mtxcli/dockerdev.py
mtxcli/gitup copy.py
mtxcli/gitup.py
mtxcli/mtdp.py
mtxcli/mtgp.py
mtxcli/mtngrok.py
mtxcli/mtpublish.py
mtxcli/setup copy.py
mtxcli/setup.py
mtxcli-0.0.178.data/scripts/dc.py
mtxcli-0.0.178.dist-info/METADATA
mtxcli-0.0.178.dist-info/WHEEL
mtxcli-0.0.178.dist-info/entry_points.txt
mtxcli-0.0.178.dist-info/top_level.txt
mtxcli-0.0.178.dist-info/RECORD
